[
{"Class":"Dec-18","Distinct":"baoan","Rental":123.0235911},
{"Class":"Jan-19","Distinct":"baoan","Rental":132.0980731},
{"Class":"Feb-19","Distinct":"baoan","Rental":123.3737821},
{"Class":"Mar-19","Distinct":"baoan","Rental":114.7218027},
{"Class":"Dec-18","Distinct":"dapeng","Rental":50},
{"Class":"Mar-19","Distinct":"dapeng","Rental":51.80532685},
{"Class":"Dec-18","Distinct":"futian","Rental":158.6868195},
{"Class":"Jan-19","Distinct":"futian","Rental":168.7008233},
{"Class":"Feb-19","Distinct":"futian","Rental":166.4749481},
{"Class":"Mar-19","Distinct":"futian","Rental":162.0537673},
{"Class":"Dec-18","Distinct":"guangming","Rental":44.10861307},
{"Class":"Jan-19","Distinct":"guangming","Rental":47.90349327},
{"Class":"Feb-19","Distinct":"guangming","Rental":47.28675135},
{"Class":"Mar-19","Distinct":"guangming","Rental":43.97505623},
{"Class":"Dec-18","Distinct":"longgang","Rental":96.62446864},
{"Class":"Jan-19","Distinct":"longgang","Rental":100.7974018},
{"Class":"Feb-19","Distinct":"longgang","Rental":98.36765591},
{"Class":"Mar-19","Distinct":"longgang","Rental":82.8675264},
{"Class":"Dec-18","Distinct":"longhua","Rental":106.3903274},
{"Class":"Jan-19","Distinct":"longhua","Rental":115.4166774},
{"Class":"Feb-19","Distinct":"longhua","Rental":128.1055258},
{"Class":"Mar-19","Distinct":"longhua","Rental":108.6788458},
{"Class":"Dec-18","Distinct":"luohu","Rental":132.1502744},
{"Class":"Jan-19","Distinct":"luohu","Rental":128.6150575},
{"Class":"Feb-19","Distinct":"luohu","Rental":130.4648507},
{"Class":"Mar-19","Distinct":"luohu","Rental":123.1402692},
{"Class":"Dec-18","Distinct":"nanshan","Rental":168.2596882},
{"Class":"Jan-19","Distinct":"nanshan","Rental":178.8765676},
{"Class":"Feb-19","Distinct":"nanshan","Rental":176.2326452},
{"Class":"Mar-19","Distinct":"nanshan","Rental":167.7837024},
{"Class":"Dec-18","Distinct":"pingshan","Rental":36.3707226},
{"Class":"Jan-19","Distinct":"pingshan","Rental":34.4238563},
{"Class":"Feb-19","Distinct":"pingshan","Rental":40.95389168},
{"Class":"Mar-19","Distinct":"pingshan","Rental":41.58268369},
{"Class":"Dec-18","Distinct":"yantian","Rental":69.60184518},
{"Class":"Jan-19","Distinct":"yantian","Rental":73.66471088},
{"Class":"Feb-19","Distinct":"yantian","Rental":64.1705046},
{"Class":"Mar-19","Distinct":"yantian","Rental":67.04566974}
]